odoo/addons/website_sale_stock_force_block/README.rst
odoo/addons/website_sale_stock_force_block/__init__.py
odoo/addons/website_sale_stock_force_block/__manifest__.py
odoo/addons/website_sale_stock_force_block/hooks.py
odoo/addons/website_sale_stock_force_block/data/demo.xml
odoo/addons/website_sale_stock_force_block/i18n/ca.po
odoo/addons/website_sale_stock_force_block/i18n/es.po
odoo/addons/website_sale_stock_force_block/i18n/fr.po
odoo/addons/website_sale_stock_force_block/i18n/nl.po
odoo/addons/website_sale_stock_force_block/i18n/website_sale_stock_force_block.pot
odoo/addons/website_sale_stock_force_block/models/__init__.py
odoo/addons/website_sale_stock_force_block/models/product_template.py
odoo/addons/website_sale_stock_force_block/models/res_config_settings.py
odoo/addons/website_sale_stock_force_block/models/sale_order.py
odoo/addons/website_sale_stock_force_block/readme/CONTRIBUTORS.rst
odoo/addons/website_sale_stock_force_block/readme/DESCRIPTION.rst
odoo/addons/website_sale_stock_force_block/readme/USAGE.rst
odoo/addons/website_sale_stock_force_block/static/description/icon.png
odoo/addons/website_sale_stock_force_block/static/description/index.html
odoo/addons/website_sale_stock_force_block/static/src/js/website_sale_stock_force_block.js
odoo/addons/website_sale_stock_force_block/static/src/js/website_sale_stock_force_block_tour.js
odoo/addons/website_sale_stock_force_block/static/src/xml/website_sale_stock_force_block.xml
odoo/addons/website_sale_stock_force_block/tests/__init__.py
odoo/addons/website_sale_stock_force_block/tests/test_website_sale_stock_force_block.py
odoo/addons/website_sale_stock_force_block/views/assets.xml
odoo/addons/website_sale_stock_force_block/views/product_template_views.xml
odoo/addons/website_sale_stock_force_block/views/templates.xml
odoo13_addon_website_sale_stock_force_block-13.0.1.0.1.dev6.dist-info/METADATA
odoo13_addon_website_sale_stock_force_block-13.0.1.0.1.dev6.dist-info/WHEEL
odoo13_addon_website_sale_stock_force_block-13.0.1.0.1.dev6.dist-info/top_level.txt
odoo13_addon_website_sale_stock_force_block-13.0.1.0.1.dev6.dist-info/RECORD
